{"cameraMode":{"drawMode":0,"name":"Shaded","section":"Shading Mode"},"sceneLighting":true,"audioPlay":false,"sceneViewState":{"m_AlwaysRefresh":false,"showFog":true,"showSkybox":true,"showFlares":true,"showImageEffects":true,"showParticleSystems":true,"showVisualEffectGraphs":true,"m_FxEnabled":true},"in2DMode":false,"pivot":{"x":-1457.0,"y":36.79999923706055,"z":1483.0},"rotation":{"x":-0.006812159903347492,"y":-0.9854106903076172,"z":0.16529837250709535,"w":-0.04051164537668228},"size":20.247295379638673,"orthographic":true}